salesforce_pandas
