Metadata-Version: 1.0
Name: salesforce-pandas
Version: 0.1
Summary: A simple salesforce API wrapper that allows you to return your query as a pandas dataframe
Home-page: idonthaveaurlyet.com
Author: Lars Hegstrom
Author-email: l.r.hegstrom@gmail.com
License: MIT
Platform: UNKNOWN
